calculate/__init__.py
calculate/cal.py
exec/__init__.py
exec/pypackage.py
util/__init__.py
util/tool.py
pypackageherbert-1.0.0.dist-info/METADATA
pypackageherbert-1.0.0.dist-info/WHEEL
pypackageherbert-1.0.0.dist-info/entry_points.txt
pypackageherbert-1.0.0.dist-info/top_level.txt
pypackageherbert-1.0.0.dist-info/RECORD
