Metadata-Version: 2.1
Name: pypackageherbert
Version: 1.0.0
Summary: 简单描述
Author: 作者
Author-email: haobinherbert@163.com
License: MIT
Platform: UNKNOWN
Classifier: Development Status :: 1 - Planning
Classifier: Intended Audience :: Developers
Classifier: Programming Language :: Python :: 3
Classifier: Operating System :: Unix
Classifier: Operating System :: MacOS :: MacOS X
Classifier: Operating System :: Microsoft :: Windows
